py4pmapp/__init__.py
py4pmapp/cleaning.py
py4pmapp/contextpipeline.py
py4pmapp/csvhelper.py
py4pmapp/ecsv.py
py4pmapp/filehelper.py
py4pmapp/log.py
py4pmapp/loghelper.py
py4pmapp/preprocessing.py
py4pmapp/runner.py
py4pmapp/utils.py
py4pmapp-0.2.1.dist-info/licenses/LICENSE
py4pmapp-0.2.1.dist-info/METADATA
py4pmapp-0.2.1.dist-info/WHEEL
py4pmapp-0.2.1.dist-info/top_level.txt
py4pmapp-0.2.1.dist-info/RECORD
