Metadata-Version: 2.4
Name: py4pmapp
Version: 0.2.1
Summary: Paquete para limpiar y preparar datos para PMApp
Author-email: Carlos Fernandez-Llatas <cfllatas@gmail.com>
Requires-Python: >=3.11
License-File: LICENSE
Requires-Dist: pandas>=1.5
Requires-Dist: chardet>=5.2.0
Requires-Dist: tqdm>=4.67.1
Dynamic: license-file
